{
    "comptes": [
        {
            "id": 0,
            "type": "jeune",
            "nom": "a",
            "prenom": "a",
            "email": "a",
            "datenaissance": "a",
            "reseau": "a",
            "engagement": "a",
            "duree": "a",
            "savoiretre": [
                "autonome",
                "passionne",
                "reflechi",
                "organise"
            ],
            "idliaison": [
                1
            ]
        },
        {
            "id": 1,
            "type": "referent",
            "nom": "b",
            "prenom": "b",
            "email": "b",
            "datenaissance": "b",
            "reseau": "b",
            "engagement": "b",
            "duree": "b",
            "savoiretre": [
                "bienveillance",
                "tolerance",
                "juste",
                "impartial"
            ],
            "idliaison": [
                0
            ]
        }
    ],
    "prochain_id": 2
}